singlecelldata/__init__.py
singlecelldata/read_data.py
singlecelldata/singlecell.py
singlecelldata-1.0.2.dist-info/LICENSE
singlecelldata-1.0.2.dist-info/METADATA
singlecelldata-1.0.2.dist-info/WHEEL
singlecelldata-1.0.2.dist-info/top_level.txt
singlecelldata-1.0.2.dist-info/RECORD
