Metadata-Version: 2.1
Name: singlecelldata
Version: 1.0.2
Summary: A python package for managing single-cell RNA-seq datasets.
Home-page: https://edwinv87.github.io/singlecelldata
Author: Edwin Vans
Author-email: info@edwinvans.com
License: UNKNOWN
Platform: UNKNOWN
Classifier: Programming Language :: Python :: 3
Classifier: License :: OSI Approved :: MIT License
Classifier: Operating System :: OS Independent
Requires-Python: >=3.6
License-File: LICENSE
